AUTHORS.rst
CONTRIBUTING.rst
HISTORY.rst
LICENSE
MANIFEST.in
README.rst
setup.cfg
setup.py
docs/Makefile
docs/authors.rst
docs/conf.py
docs/contributing.rst
docs/history.rst
docs/index.rst
docs/installation.rst
docs/make.bat
docs/modules.rst
docs/pyactiviti.rst
docs/readme.rst
docs/usage.rst
pyactiviti/__init__.py
pyactiviti/exceptions.py
pyactiviti/pyactiviti.py
pyactiviti.egg-info/PKG-INFO
pyactiviti.egg-info/SOURCES.txt
pyactiviti.egg-info/dependency_links.txt
pyactiviti.egg-info/not-zip-safe
pyactiviti.egg-info/requires.txt
pyactiviti.egg-info/top_level.txt
tests/__init__.py
tests/common.py
tests/test_deployment.py
tests/test_group.py
tests/test_url.py
tests/test_user.py