Metadata-Version: 1.1
Name: pyactiviti
Version: 0.1.0
Summary: An SDK that helps with interacting with Activiti.
Home-page: https://github.com/matrixise/pyactiviti
Author: Stephane Wirtel
Author-email: stephane@wirtel.be
License: BSD
Keywords: pyactiviti
Platform: UNKNOWN
Classifier: Development Status :: 2 - Pre-Alpha
Classifier: Intended Audience :: Developers
Classifier: License :: OSI Approved :: BSD License
Classifier: Natural Language :: English
Classifier: Programming Language :: Python :: 2
Classifier: Programming Language :: Python :: 2.7
